sysdescrparser/__init__.py
sysdescrparser/a10.py
sysdescrparser/a10_acos.py
sysdescrparser/arista.py
sysdescrparser/arista_eos.py
sysdescrparser/aruba.py
sysdescrparser/brocade.py
sysdescrparser/brocade_ironware.py
sysdescrparser/brocade_networkos.py
sysdescrparser/brocade_serveriron.py
sysdescrparser/cisco.py
sysdescrparser/cisco_asa.py
sysdescrparser/cisco_ios.py
sysdescrparser/cisco_iosxe.py
sysdescrparser/cisco_iosxr.py
sysdescrparser/cisco_nxos.py
sysdescrparser/citrix.py
sysdescrparser/citrix_netscaler.py
sysdescrparser/extreme.py
sysdescrparser/extreme_xos.py
sysdescrparser/fortinet.py
sysdescrparser/fortinet_fortios.py
sysdescrparser/foundry.py
sysdescrparser/foundry_ironware.py
sysdescrparser/freebsd.py
sysdescrparser/hp.py
sysdescrparser/hp_procurve.py
sysdescrparser/iij.py
sysdescrparser/iij_seil.py
sysdescrparser/juniper.py
sysdescrparser/juniper_junos.py
sysdescrparser/juniper_screenos.py
sysdescrparser/linux.py
sysdescrparser/mikrotik_routeros.py
sysdescrparser/paloalto.py
sysdescrparser/paloalto_panos.py
sysdescrparser/sun.py
sysdescrparser/sun_sunos.py
sysdescrparser/sysdescr.py
sysdescrparser/sysdescrparser.py
sysdescrparser/unknown.py
sysdescrparser/yamaha.py
sysdescrparser/yamaha_rtx.py
sysdescrparser/tests/__init__.py
sysdescrparser/tests/test_sysdescrparser.py
sysdescrparser/utils/__init__.py
sysdescrparser/utils/utils.py
snmpsysdescrparser-0.1.21.dist-info/LICENSE
snmpsysdescrparser-0.1.21.dist-info/METADATA
snmpsysdescrparser-0.1.21.dist-info/WHEEL
snmpsysdescrparser-0.1.21.dist-info/top_level.txt
snmpsysdescrparser-0.1.21.dist-info/RECORD
